README.rst
setup.py
zzyzx/__init__.py
zzyzx/backup.py
zzyzx/cli.py
zzyzx/commit_message.txt
zzyzx/markdownify.py
zzyzx/md.py
zzyzx/util.py
zzyzx.egg-info/PKG-INFO
zzyzx.egg-info/SOURCES.txt
zzyzx.egg-info/dependency_links.txt
zzyzx.egg-info/entry_points.txt
zzyzx.egg-info/not-zip-safe
zzyzx.egg-info/requires.txt
zzyzx.egg-info/top_level.txt