Metadata-Version: 1.1
Name: zzyzx
Version: 2016.6.0
Summary: A simple IMAP Notes backup tool.
Home-page: http://github.com/ambv/zzyzx
Author: Łukasz Langa
Author-email: lukasz@langa.pl
License: UNKNOWN
Platform: any
Classifier: Development Status :: 3 - Alpha
Classifier: License :: OSI Approved :: MIT License
Classifier: Natural Language :: English
Classifier: Programming Language :: Python
Classifier: Programming Language :: Python :: 3 :: Only
